src/holographic_memory/__init__.py
src/holographic_memory/associative_memory.py
src/holographic_memory/capacity_analysis.py
src/holographic_memory/cleanup_operations.py
src/holographic_memory/composite_memory.py
src/holographic_memory/compositional_structures.py
src/holographic_memory/configuration.py
src/holographic_memory/holographic_cleanup_config.py
src/holographic_memory/plate_correlation_cleanup.py
src/holographic_memory/plate_correlation_cleanup_complete.py
src/holographic_memory/vector_operations.py
src/holographic_memory/vector_symbolic.py
src/holographic_memory/vsa_comprehensive_config.py
src/holographic_memory/associative_modules/associative_cleanup.py
src/holographic_memory/associative_modules/hopfield_cleanup.py
src/holographic_memory/associative_modules/memory_structures.py
src/holographic_memory/compositional_modules/__init__.py
src/holographic_memory/compositional_modules/analogy_engine.py
src/holographic_memory/compositional_modules/capacity_monitor.py
src/holographic_memory/compositional_modules/compositional_cleanup.py
src/holographic_memory/compositional_modules/reduced_representations.py
src/holographic_memory/compositional_modules/structure_creation.py
src/holographic_memory/compositional_modules/structure_primitives.py
src/holographic_memory/compositional_modules/structure_types.py
src/holographic_memory/config/__init__.py
src/holographic_memory/config/config_classes.py
src/holographic_memory/config/defaults.py
src/holographic_memory/config/enums.py
src/holographic_memory/core/__init__.py
src/holographic_memory/core/associative_memory.py
src/holographic_memory/core/compositional_hrr.py
src/holographic_memory/core/holographic_memory.py
src/holographic_memory/core/hrr_operations.py
src/holographic_memory/core/memory_management.py
src/holographic_memory/old_archive/hm_modules/__init__.py
src/holographic_memory/old_archive/hm_modules/capacity_analysis.py
src/holographic_memory/old_archive/hm_modules/cleanup_operations.py
holographic_memory-1.4.0.dist-info/METADATA
holographic_memory-1.4.0.dist-info/WHEEL
holographic_memory-1.4.0.dist-info/licenses/LICENSE
holographic_memory-1.4.0.dist-info/RECORD
